queenbee/__init__.py
queenbee/base/__init__.py
queenbee/base/basemodel.py
queenbee/base/metadata.py
queenbee/base/parser.py
queenbee/base/request.py
queenbee/base/variable.py
queenbee/cli/__init__.py
queenbee/cli/assets/new-plugin.yaml
queenbee/cli/assets/new-recipe.yaml
queenbee/cli/assets/queenbee-art.txt
queenbee/cli/config/__init__.py
queenbee/cli/config/auth.py
queenbee/cli/config/view.py
queenbee/cli/context.py
queenbee/cli/plugin/__init__.py
queenbee/cli/plugin/lint.py
queenbee/cli/plugin/new.py
queenbee/cli/plugin/package.py
queenbee/cli/recipe/__init__.py
queenbee/cli/recipe/install.py
queenbee/cli/recipe/link.py
queenbee/cli/recipe/lint.py
queenbee/cli/recipe/new.py
queenbee/cli/recipe/package.py
queenbee/cli/repository/__init__.py
queenbee/cli/repository/index.py
queenbee/cli/repository/init.py
queenbee/cli/repository/manage.py
queenbee/cli/repository/search.py
queenbee/cli/repository/serve.py
queenbee/config/__init__.py
queenbee/config/auth.py
queenbee/config/repositories.py
queenbee/env/os.py
queenbee/io/__init__.py
queenbee/io/artifact_source.py
queenbee/io/common.py
queenbee/io/inputs/__init__.py
queenbee/io/inputs/alias.py
queenbee/io/inputs/dag.py
queenbee/io/inputs/function.py
queenbee/io/inputs/job.py
queenbee/io/inputs/step.py
queenbee/io/inputs/task.py
queenbee/io/outputs/__init__.py
queenbee/io/outputs/alias.py
queenbee/io/outputs/dag.py
queenbee/io/outputs/function.py
queenbee/io/outputs/step.py
queenbee/io/outputs/task.py
queenbee/io/reference.py
queenbee/job/__init__.py
queenbee/job/job.py
queenbee/job/result.py
queenbee/job/run.py
queenbee/job/status.py
queenbee/plugin/__init__.py
queenbee/plugin/function.py
queenbee/plugin/plugin.py
queenbee/recipe/__init__.py
queenbee/recipe/dag.py
queenbee/recipe/dependency.py
queenbee/recipe/recipe.py
queenbee/recipe/task.py
queenbee/repository/__init__.py
queenbee/repository/index.py
queenbee/repository/package.py
queenbee-1.28.2.dist-info/LICENSE
queenbee-1.28.2.dist-info/METADATA
queenbee-1.28.2.dist-info/WHEEL
queenbee-1.28.2.dist-info/entry_points.txt
queenbee-1.28.2.dist-info/RECORD
