Metadata-Version: 2.1
Name: queenbee
Version: 1.28.2
Summary: Queenbee is a workflow language and a package manager for creating DAG workflows which empowers all workflow libraries in Ladybug Tools!
Home-page: https://github.com/pollination/queenbee
License: MIT
Author: Ladybug Tools
Author-email: info@ladybug.tools
Requires-Python: >=3.7,<4.0
Classifier: License :: OSI Approved :: MIT License
Classifier: Operating System :: OS Independent
Classifier: Programming Language :: Python :: 3
Classifier: Programming Language :: Python :: 3.7
Classifier: Programming Language :: Python :: 3.8
Classifier: Programming Language :: Python :: 3.9
Classifier: Programming Language :: Python :: 3.10
Classifier: Programming Language :: Python :: 3.11
Classifier: Programming Language :: Python :: 3.12
Classifier: Programming Language :: Python :: 3.13
Classifier: Programming Language :: Python :: Implementation :: CPython
Provides-Extra: cli
Requires-Dist: click (>=8.1.7,<9.0.0) ; extra == "cli"
Requires-Dist: click-plugins (>=1.1.1,<2.0.0) ; extra == "cli"
Requires-Dist: jsonschema (>=4.17.3)
Requires-Dist: pydantic (<2.0)
Requires-Dist: pyyaml (>=6.0)
Project-URL: Documentation, https://pollination.github.io/queenbee/
Project-URL: Repository, https://github.com/pollination/queenbee
